{
  "Url": "https://www.diffordsguide.com/cocktails/recipe/3466/bermondsey-minute",
  "Name": "Bermondsey Minute",
  "Glass": "",
  "Ingredients": [
    "60 ml Patrón Reposado tequila",
    "20 ml Carpano Antica Formula Vermouth",
    "7.5 ml Luxardo Maraschino liqueur",
    "7.5 ml Lavender sugar syrup",
    "0.2 ml Bob's Lavender Bitters optional",
    "10 ml Chilled water omit if using wet ice"
  ],
  "Instructions": [
    "Select and pre-chill a Coupe glass .",
    "Prepare garnish of lemon and orange zest twists, and coffee beans.",
    "STIR all ingredients with ice.",
    "FINE STRAIN into chilled glass.",
    "EXPRESS orange and lemon zests over cocktail, and discard.",
    "Float 3 coffee beans for garnish."
  ],
  "Review": "Tequila and lavender are a match made in heaven, made more complex with herbal wine notes from the vermouth and aromatised by delicately fruity maraschino cherry. Dilution is so key to this cocktail that please consider serving on-the-rocks.",
  "History": "Created in Bermondsey, London in 2014 by yours truly and adapted from the New York Minute , originally by Luke Whearty at Der Raum, Melbourne.",
  "Nutrition": "One serving of Bermondsey Minute contains 205 calories",
  "Alcohol_Content": [
    [
      "1.7 standard drinks"
    ],
    [
      "22.28% alc./vol. (22.28° proof)"
    ],
    [
      "23.4 grams of pure alcohol"
    ]
  ],
  "Garnish": ""
}