{
  "Url": "https://www.diffordsguide.com/cocktails/recipe/3115/dry-martini-215-ratio-sopping-wet",
  "Name": "Dry Martini (2:1.5 ratio) Sopping Wet",
  "Glass": "Martini glass",
  "Ingredients": [
    "60 ml Hayman's London Dry Gin",
    "45 ml Strucchi Dry Vermouth",
    "2 dash Orange Bitters by Angostura optional"
  ],
  "Instructions": [
    "Select and pre-chill a Martini glass .",
    "Prepare garnish of chilled Fragata Green Olive on stick or lemon zest twist.",
    "STIR all ingredients with ice.",
    "FINE STRAIN into chilled glass."
  ],
  "Review": "Herbal vermouth flavours pervade this Sopping Wet Martini.",
  "History": "There is considerable debate about the origin of the Martini. See the Martini Cocktail And Its Evolution .",
  "Nutrition": "One serving of Dry Martini (2:1.5 ratio) Sopping Wet contains 185 calories",
  "Alcohol_Content": [
    [
      "1.9 standard drinks"
    ],
    [
      "24.6% alc./vol. (24.6° proof)"
    ],
    [
      "26 grams of pure alcohol"
    ]
  ],
  "Garnish": ""
}