{
  "Url": "https://www.diffordsguide.com/cocktails/recipe/693/eclipse",
  "Name": "Eclipse",
  "Glass": "Collins glass",
  "Ingredients": [
    "12 fresh Raspberries",
    "60 ml Bourbon whiskey",
    "30 ml Giffard Framboise de Ronce (raspberry liqueur)",
    "15 ml Lime juice (freshly squeezed)",
    "60 ml Cranberry juice (sweetened)"
  ],
  "Instructions": [
    "MUDDLE raspberries in base of shaker. Add other ingredients, SHAKE with ice and fine strain into glass filled with crushed ice. Serve with straws."
  ],
  "Review": "A fruity summer cooler which I challenge anyone not to like.",
  "History": "Signature cocktail at the chain of Eclipse Bars, London, England.",
  "Nutrition": "",
  "Alcohol_Content": [],
  "Garnish": "Raspberries & mint sprig"
}