{
  "Url": "https://www.diffordsguide.com/cocktails/recipe/4277/gin-tonica",
  "Name": "Gin Tonica",
  "Glass": "Copa glass",
  "Ingredients": [
    "60 ml Hayman's London Dry Gin",
    "150 ml Thomas Henry Tonic Water"
  ],
  "Instructions": [
    "Select and pre-chill a Copa glass .",
    "Prepare garnish of lemon zest twist, lime wedge & 3 cardamom pods.",
    "POUR all ingredients into ice-filled glass.",
    "Lightly stir."
  ],
  "Review": "Something of a Spanish phenomenon, where the G&T (which in England has been traditionally served in a tall slim Collins glass) tends to be served in a huge goldfish bowl of a glass – big enough to house garnishes ranging from cardamom pods and juniper berries to fruit peels and slices of ginger.",
  "History": "",
  "Nutrition": "One serving of Gin Tonica contains 191 calories",
  "Alcohol_Content": [
    [
      "1.4 standard drinks"
    ],
    [
      "9.27% alc./vol. (9.27° proof)"
    ],
    [
      "19.5 grams of pure alcohol"
    ]
  ],
  "Garnish": ""
}