{
  "Url": "https://www.diffordsguide.com/cocktails/recipe/891/grand-sazerac",
  "Name": "Grand Sazerac",
  "Glass": "Old-fashioned glass",
  "Ingredients": [
    "10 ml La Fée Parisienne absinthe",
    "Top up with Chilled water",
    "45 ml Grand Marnier or other cognac orange liqueur",
    "45 ml Bourbon whiskey",
    "2 dash Angostura Aromatic Bitters",
    "3 dash Peychaud's or other Creole-style bitters"
  ],
  "Instructions": [
    "POUR absinthe into ice-filled glass and TOP with water. Leave the mixture to stand in the glass. Separately, STIR other ingredients with ice. Finally, discard contents of absinthe-washed glass and strain contents of shaker into absinthe-washed glass. (No ice in the finished drink.)"
  ],
  "Review": "An orange twist on the classic Sazerac .",
  "History": "Created in 2004 by yours truly in London, England. Sazerac cocktail history and recipe variations",
  "Nutrition": "One serving of Grand Sazerac contains 265 calories",
  "Alcohol_Content": [
    [
      "2.4 standard drinks"
    ],
    [
      "33.06% alc./vol. (33.06° proof)"
    ],
    [
      "33.6 grams of pure alcohol"
    ]
  ],
  "Garnish": ""
}