{
  "Url": "https://www.diffordsguide.com/cocktails/recipe/2679/greenbelt",
  "Name": "Greenbelt",
  "Glass": "Collins glass",
  "Ingredients": [
    "10 fresh Green grapes (seedless)",
    "50 ml BarSol Mosto Verde Italia Pisco",
    "25 ml Elderflower liqueur",
    "60 ml Brut champagne/sparkling wine chilled"
  ],
  "Instructions": [
    "MUDDLE grapes in base of shaker. Add pisco and elderflower liqueur, SHAKE with ice and fine strain into ice-filled glass. TOP with sparkling wine."
  ],
  "Review": "Tastes as green and fresh as it looks. Also, floral and refreshing.",
  "History": "Created in 2007 by yours truly in London, England.",
  "Nutrition": "",
  "Alcohol_Content": [],
  "Garnish": "3 skewered white grapes"
}