{
  "Url": "https://www.diffordsguide.com/cocktails/recipe/2684/hearst-martini",
  "Name": "Hearst Martini",
  "Glass": "Martini glass",
  "Ingredients": [
    "60 ml Hayman's London Dry Gin",
    "30 ml Strucchi Rosso Vermouth",
    "1 dash Orange Bitters by Angostura",
    "1 dash Angostura Aromatic Bitters"
  ],
  "Instructions": [
    "Select and pre-chill a Martini glass .",
    "Prepare garnish of orange zest twist.",
    "STIR all ingredients with ice.",
    "FINE STRAIN into chilled glass.",
    "EXPRESS orange zest twist over the cocktail and use as garnish."
  ],
  "Review": "A fantastically wet, sweet and aromatic Martini.",
  "History": "This was supposedly a favourite of hacks who worked for the American newspaper magnate, William Randolph Hearst, and is believed to have been created at New York's Waldorf-Astoria. It is nicknamed 'The Disgruntled Journalist' and indeed, is not dissimilar to a Journalist cocktail with extra bitters. Dry Martini history and evolution",
  "Nutrition": "One serving of Hearst Martini contains 178 calories",
  "Alcohol_Content": [
    [
      "1.7 standard drinks"
    ],
    [
      "25.85% alc./vol. (25.85° proof)"
    ],
    [
      "23.4 grams of pure alcohol"
    ]
  ],
  "Garnish": ""
}