{
  "Url": "https://www.diffordsguide.com/cocktails/recipe/2444/hobson",
  "Name": "Hobson",
  "Glass": "Old-fashioned glass",
  "Ingredients": [
    "60 ml Hayman's Sloe Gin",
    "30 ml De Kuyper Triple Sec (40%)",
    "7.5 ml La Fée Parisienne absinthe"
  ],
  "Instructions": [
    "Select and pre-chill an Old-fashioned glass .",
    "Prepare garnish of orange slice .",
    "SHAKE all ingredients with ice.",
    "STRAIN into glass filled with crushed ice."
  ],
  "Review": "Unbalanced towards sweetness. With drinks like this you can see why Hobson chose to be an abstainer. Originally served 'straight-up' but better over crushed ice.",
  "History": "Named after Richmond Pearson Hobson (1870-1937) the United States Navy Rear Admiral and not Thomas Hobson (1545 - 1631) from Cambridge, England who gave rise to the term 'Hobson's choice'. R.P. Hopson was a hero of the American-Spanish war of 1898 who went on to became a Congressman. An ardent abstainer, Hobson has been called 'The Father of American Prohibition' due of his advocacy for criminalizing alcohol and other drugs and was a prolific author on this subject.",
  "Nutrition": "",
  "Alcohol_Content": [
    [
      "1.7 standard drinks"
    ],
    [
      "24.66% alc./vol. (24.66° proof)"
    ],
    [
      "24 grams of pure alcohol"
    ]
  ],
  "Garnish": ""
}