{
  "Url": "https://www.diffordsguide.com/cocktails/recipe/3325/honey-cobbler",
  "Name": "Honey Cobbler",
  "Glass": "Goblet glass",
  "Ingredients": [
    "45 ml Blended Scotch whisky",
    "30 ml Claret wine (Bordeaux red)",
    "7.5 ml Joseph Cartron Double Crème de Cassis de Bourgogne",
    "10 ml Honey syrup (3 parts honey to 1 water by weight)"
  ],
  "Instructions": [
    "Select and pre-chill a Goblet glass .",
    "Prepare garnish of mint sprig and berries.",
    "SHAKE all ingredients with ice.",
    "STRAIN into glass filled with crushed ice.",
    "Serve with a straw."
  ],
  "Review": "Dry wine tannins and smoky scotch balance rich honey and blackcurrant liqueur.",
  "History": "See: Cobbler cocktails history .",
  "Nutrition": "One serving of Honey Cobbler contains 172 calories",
  "Alcohol_Content": [
    [
      "1.2 standard drinks"
    ],
    [
      "18.3% alc./vol. (18.3° proof)"
    ],
    [
      "16.9 grams of pure alcohol"
    ]
  ],
  "Garnish": ""
}