{
  "Url": "https://www.diffordsguide.com/cocktails/recipe/1148/lemon-meringue-pietini",
  "Name": "Lemon Meringue Pie'tini",
  "Glass": "Coupe glass",
  "Ingredients": [
    "30 ml Pallini Limoncello liqueur",
    "30 ml Sugar syrup 'rich' (2 sugar to 1 water, 65.0°Brix)",
    "30 ml Lemon juice (freshly squeezed)",
    "60 ml Single cream/half-and-half",
    "15 ml Licor 43 Original liqueur"
  ],
  "Instructions": [
    "Select and pre-chill a Coupe glass .",
    "Apply pie rim by wiping the outside edge of glass rim with 50:50 mix of cream and sugar syrup, then dip into crunched up Graham Cracker or digestive biscuits.",
    "SHAKE first 3 ingredients with ice.",
    "FINE STRAIN strain into chilled and rimmed glass.",
    "DRY SHAKE (without ice) cream and liqueur to mix and whip.",
    "FLOAT cream & liqueur mix by pouring over back of spoon."
  ],
  "Review": "Rich and syrupy base sipped through a vanilla cream topping.",
  "History": "Created by Michael Waterhouse at Dylan Prime in Manhattan, New York City.",
  "Nutrition": "One serving of Lemon Meringue Pie'tini contains 269 calories",
  "Alcohol_Content": [
    [
      "0.7 standard drinks"
    ],
    [
      "5.55% alc./vol. (5.55° proof)"
    ],
    [
      "9.2 grams of pure alcohol"
    ]
  ],
  "Garnish": ""
}