{
  "Url": "https://www.diffordsguide.com/cocktails/recipe/2466/lemon-lime-and-bitters",
  "Name": "Lemon Lime & Bitters",
  "Glass": "Collins glass",
  "Ingredients": [
    "15 ml Lime juice (freshly squeezed)",
    "150 ml Lemonade",
    "4 dash Angostura Aromatic Bitters"
  ],
  "Instructions": [
    "POUR lime and lemonade into ice-filled glass and briefly stir. DASH bitters onto surface of drink and serve with a straw so drinker can stir in the bitters."
  ],
  "Review": "*NOTE: Contains minute levels of alcohol due to use of aromatic bitters but is considered an alcohol-free cocktail.",
  "History": "Very popular in its homeland, Australia.",
  "Nutrition": "One serving of Lemon Lime & Bitters contains 54 calories",
  "Alcohol_Content": [
    [
      "0 standard drinks"
    ],
    [
      "0.26% alc./vol. (0.26° proof)"
    ],
    [
      "0.4 grams of pure alcohol"
    ]
  ],
  "Garnish": "Lime wedge"
}