{
  "Url": "https://www.diffordsguide.com/cocktails/recipe/1180/livingstone",
  "Name": "Livingstone",
  "Glass": "",
  "Ingredients": [
    "60 ml Hayman's London Dry Gin",
    "30 ml Strucchi Dry Vermouth",
    "5 ml Sugar syrup 'rich' (2 sugar to 1 water, 65.0°Brix)"
  ],
  "Instructions": [
    "Select and pre-chill a Martini glass .",
    "Prepare garnish of lemon zest twist.",
    "STIR all ingredients with ice.",
    "FINE STRAIN into chilled glass.",
    "EXPRESS lemon zest twist over the cocktail and use as garnish."
  ],
  "Review": "The classic gin and vermouth Dry Martini made not so dry and a tad more approachable by a splash of sugar.",
  "History": "This vintage cocktail is named after Doctor Livingstone, the famous African missionary.",
  "Nutrition": "One serving of Livingstone contains 184 calories",
  "Alcohol_Content": [
    [
      "1.7 standard drinks"
    ],
    [
      "24.97% alc./vol. (24.97° proof)"
    ],
    [
      "23.7 grams of pure alcohol"
    ]
  ],
  "Garnish": ""
}