{
  "Url": "https://www.diffordsguide.com/cocktails/recipe/2474/looks-familiar",
  "Name": "Looks Familiar",
  "Glass": "Old-fashioned glass",
  "Ingredients": [
    "15 ml Torabhaig Peated Single Malt Whisky",
    "60 ml Patrón Silver blanco tequila",
    "15 ml Agave syrup",
    "2 dash Angostura Aromatic Bitters",
    "7.5 ml Amer Picon"
  ],
  "Instructions": [
    "STIR malt with ice and then strain and discard excess to leave the ice and mixing glass coated. Add other ingredients and STIR with the coated ice. Strain into ice-filled glass."
  ],
  "Review": "I defy you not to love this herbal bittersweet tequila-laced concoction.",
  "History": "Created by Jake Burger at Jake's Bar, Leeds, England.",
  "Nutrition": "One serving of Looks Familiar contains 236 calories",
  "Alcohol_Content": [
    [
      "1.8 standard drinks"
    ],
    [
      "26.28% alc./vol. (26.28° proof)"
    ],
    [
      "25.8 grams of pure alcohol"
    ]
  ],
  "Garnish": "Orange zest twist"
}