{
  "Url": "https://www.diffordsguide.com/cocktails/recipe/3190/lychee-martini",
  "Name": "Lychee Martini",
  "Glass": "",
  "Ingredients": [
    "25 ml Hayman's London Dry Gin",
    "25 ml Ketel One Vodka",
    "25 ml Kwai Feh lychee liqueur",
    "15 ml Strucchi Dry Vermouth",
    "1 dash Peychaud's or other Creole-style bitters",
    "6 drop Saline solution 4:1 (20g sea salt to 80g water)"
  ],
  "Instructions": [
    "Select and pre-chill a Martini glass .",
    "Prepare garnish of skewered lychee.",
    "STIR all ingredients with ice.",
    "STRAIN into chilled glass.",
    "Garnish with skewered lychee."
  ],
  "Review": "As the name promises, lychee fruitiness shines throughout this dry (fruity but not sweet) Martini.",
  "History": "Recipe by yours truly in May 2025.",
  "Nutrition": "One serving of Lychee Martini contains 154 calories",
  "Alcohol_Content": [
    [
      "1.6 standard drinks"
    ],
    [
      "24.47% alc./vol. (24.47° proof)"
    ],
    [
      "22.1 grams of pure alcohol"
    ]
  ],
  "Garnish": ""
}