{
  "Url": "https://www.diffordsguide.com/cocktails/recipe/1226/major-bailey-2",
  "Name": "Major Bailey #2",
  "Glass": "Sling glass",
  "Ingredients": [
    "60 ml Light white rum (charcoal-filtered 1-4 years old)",
    "30 ml De Kuyper Triple Sec (40%)",
    "30 ml Pineapple juice",
    "15 ml Lemon juice (freshly squeezed)",
    "7.5 ml Sugar syrup 'rich' (2 sugar to 1 water, 65.0°Brix)"
  ],
  "Instructions": [
    "Select and pre-chill a Sling glass .",
    "Prepare mint sprigs for garnish.",
    "BLEND all ingredients with 7oz scoop of crushed ice.",
    "Serve with straws.",
    "Garnish with mint sprigs bouquet."
  ],
  "Review": "Made well this is a long, fruity, brilliant frozen Daquiri.",
  "History": "Adapted from a recipe in Victor Bergeron 's 1972 Trader Vic's Bartender's Guide, Revised .",
  "Nutrition": "One serving of Major Bailey #2 contains 238 calories",
  "Alcohol_Content": [
    [
      "1.9 standard drinks"
    ],
    [
      "18.44% alc./vol. (18.44° proof)"
    ],
    [
      "26.3 grams of pure alcohol"
    ]
  ],
  "Garnish": ""
}