{
  "Url": "https://www.diffordsguide.com/cocktails/recipe/1304/mexican-martini-anejo-margarita",
  "Name": "Mexican Martini (Añejo Margarita)",
  "Glass": "Martini glass",
  "Ingredients": [
    "45 ml Patrón Añejo tequila",
    "20 ml Lime juice (freshly squeezed)",
    "10 ml De Kuyper Triple Sec (40%)",
    "7.5 ml Agave syrup"
  ],
  "Instructions": [
    "Select and pre-chill a Martini glass .",
    "Prepare garnish of jalapeño stuffed Fragata Green Olives .",
    "SHAKE all ingredients with ice.",
    "FINE STRAIN into chilled glass."
  ],
  "Review": "Basically, a top-shelf Margarita garnished with jalapeño stuffed olives.",
  "History": "",
  "Nutrition": "One serving of Mexican Martini (Añejo Margarita) contains 146 calories",
  "Alcohol_Content": [
    [
      "1.2 standard drinks"
    ],
    [
      "19.61% alc./vol. (19.61° proof)"
    ],
    [
      "16.2 grams of pure alcohol"
    ]
  ],
  "Garnish": ""
}