{
  "Url": "https://www.diffordsguide.com/cocktails/recipe/1348/monarch-martini",
  "Name": "Monarch Martini",
  "Glass": "Martini glass",
  "Ingredients": [
    "7 fresh Mint leaves",
    "60 ml Hayman's London Dry Gin",
    "15 ml Elderflower liqueur",
    "15 ml Lemon juice (freshly squeezed)",
    "7.5 ml Sugar syrup 'rich' (2 sugar to 1 water, 65.0°Brix)",
    "2 dash Peach bitters"
  ],
  "Instructions": [
    "MUDDLE mint (just to bruise) in base of shaker. Add other ingredients, SHAKE with ice and fine strain into chilled glass."
  ],
  "Review": "Wonderfully floral and minty - worthy of a right royal drinker.",
  "History": "Created in 2003 by Douglas Ankrah at Townhouse bar in Knighsbridge, London, England.",
  "Nutrition": "",
  "Alcohol_Content": [],
  "Garnish": "Lemon zest twist"
}