{
  "Url": "https://www.diffordsguide.com/cocktails/recipe/1354/monks-habit",
  "Name": "Monk's Habit",
  "Glass": "Collins glass",
  "Ingredients": [
    "45 ml Light white rum (charcoal-filtered 1-4 years old)",
    "15 ml De Kuyper Triple Sec (40%)",
    "30 ml Hazelnut liqueur",
    "90 ml Pineapple juice",
    "7.5 ml Grenadine/pomegranate syrup"
  ],
  "Instructions": [
    "Select and pre-chill a Collins glass .",
    "Prepare orange slice for garnish.",
    "SHAKE all ingredients with ice.",
    "STRAIN into ice-filled glass.",
    "Garnish with orange slice."
  ],
  "Review": "Fruit and nut laced with rum. Slightly sweet.",
  "History": "",
  "Nutrition": "One serving of Monk's Habit contains 278 calories",
  "Alcohol_Content": [
    [
      "1.6 standard drinks"
    ],
    [
      "11.76% alc./vol. (11.76° proof)"
    ],
    [
      "22.1 grams of pure alcohol"
    ]
  ],
  "Garnish": ""
}