{
  "Url": "https://www.diffordsguide.com/cocktails/recipe/1390/navigator",
  "Name": "Navigator",
  "Glass": "",
  "Ingredients": [
    "60 ml Hayman's London Dry Gin",
    "22.5 ml Pallini Limoncello liqueur",
    "37.5 ml Pink grapefruit juice (freshly squeezed)"
  ],
  "Instructions": [
    "Select and pre-chill a Coupe glass .",
    "Prepare garnish of lemon zest twist.",
    "SHAKE all ingredients with ice.",
    "FINE STRAIN into chilled glass.",
    "EXPRESS lemon zest twist over the cocktail and use as garnish."
  ],
  "Review": "This fruity, grapefruit-led drink is pleasantly bitter and sour.",
  "History": "Created in 2005 by Jamie Terrell, London, England.",
  "Nutrition": "One serving of Navigator contains 157 calories",
  "Alcohol_Content": [
    [
      "1.6 standard drinks"
    ],
    [
      "18.73% alc./vol. (18.73° proof)"
    ],
    [
      "22.5 grams of pure alcohol"
    ]
  ],
  "Garnish": ""
}