{
  "Url": "https://www.diffordsguide.com/cocktails/recipe/2516/negroni-spumante",
  "Name": "Negroni Spumante",
  "Glass": "Old-fashioned glass",
  "Ingredients": [
    "30 ml Strucchi Rosso Vermouth",
    "30 ml Strucchi Red Bitter (Campari-style liqueur)",
    "30 ml Hayman's London Dry Gin",
    "Top up with Fiol Extra Dry Prosecco"
  ],
  "Instructions": [
    "Select and pre-chill an Old-fashioned glass .",
    "Prepare garnish of orange zest twist.",
    "POUR first 3 ingredients into ice-filled glass.",
    "STIR .",
    "TOP with sparkling wine.",
    "EXPRESS orange zest twist over the cocktail and use as garnish."
  ],
  "Review": "A Negroni lengthened with sparkling wine. Every Negroni drinker should try this variation",
  "History": "The history and other recipes for the Negroni cocktail can be found on our Negroni cocktail page.",
  "Nutrition": "One serving of Negroni Spumante contains 183 calories",
  "Alcohol_Content": [
    [
      "1.4 standard drinks"
    ],
    [
      "21.57% alc./vol. (21.57° proof)"
    ],
    [
      "19.4 grams of pure alcohol"
    ]
  ],
  "Garnish": ""
}