{
  "Url": "https://www.diffordsguide.com/cocktails/recipe/3963/prohibition-daisy",
  "Name": "Prohibition Daisy",
  "Glass": "Old-fashioned glass",
  "Ingredients": [
    "30 ml Orange juice (freshly squeezed)",
    "15 ml Lime juice (freshly squeezed)",
    "15 ml Lemon juice (freshly squeezed)",
    "30 ml Pineapple juice",
    "30 ml Raspberry (framboise) sugar syrup"
  ],
  "Instructions": [
    "SHAKE all ingredients with ice and strain into glass filled with crushed ice. CHURN drink and serve with straws."
  ],
  "Review": "A lightly sweetened fruit smoothie with orange, pineapple, and raspberry along with lemon and lime which provide balancing citrus acidity.",
  "History": "",
  "Nutrition": "One serving of Prohibition Daisy contains 136 calories",
  "Alcohol_Content": [
    [
      "0 standard drinks"
    ],
    [
      "0% alc./vol. (0° proof)"
    ],
    [
      "0 grams of pure alcohol"
    ]
  ],
  "Garnish": "Pineapple wedge, orange wheel & raspberries"
}