{
  "Url": "https://www.diffordsguide.com/cocktails/recipe/4174/rain-or-shine",
  "Name": "Rain or Shine",
  "Glass": "Highball (max 10oz/300ml)",
  "Ingredients": [
    "45 ml Bacardi Carta Blanca Superior White Rum",
    "30 ml Carrot juice (freshly extracted)",
    "15 ml Guava juice drink",
    "15 ml Green mint (menthe verte)/Peppermint syrup",
    "15 ml Lime juice (freshly squeezed)",
    "1 dash Bob's Grapefruit Bitters"
  ],
  "Instructions": [
    "SHAKE all ingredients with ice and strain into glass filled with crushed ice."
  ],
  "Review": "",
  "History": "Created for Bacardí Legacy 2017 by Orman Bag-ao at Long Bar, Raffles and Fairmont Hotel Makati in Manila, Philippines.",
  "Nutrition": "One serving of Rain or Shine contains 148 calories",
  "Alcohol_Content": [
    [
      "0.9 standard drinks"
    ],
    [
      "10.37% alc./vol. (10.37° proof)"
    ],
    [
      "12.5 grams of pure alcohol"
    ]
  ],
  "Garnish": "Dehydrated carrot & mint sprig"
}