{
  "Url": "https://www.diffordsguide.com/cocktails/recipe/4023/ru-yi-knot",
  "Name": "Ru-Yi Knot",
  "Glass": "Coupe glass",
  "Ingredients": [
    "11⁄2inch Cucumber (fresh)",
    "45 ml Bacardi Carta Blanca Superior White Rum",
    "10 ml Lemon juice (freshly squeezed)",
    "30 ml Tomato juice",
    "30 ml *Special ingredient #1 (see above)"
  ],
  "Instructions": [
    "MUDDLE cucumber in base of shaker. Add other ingredients, shake with ice and fine strain into chilled glass. Special ingredient #1 : Homemade syrup with mint tea"
  ],
  "Review": "",
  "History": "The Chinese Bacardí Legacy 2013 winning cocktail created by Yao Zong \"Foxyie\" Huang at Bar The Soul in China.",
  "Nutrition": "",
  "Alcohol_Content": [],
  "Garnish": "Black pepper & fresh cucumber"
}