{
  "Url": "https://www.diffordsguide.com/cocktails/recipe/2856/scottish-gypsy",
  "Name": "Scottish Gypsy",
  "Glass": "Nick & Nora glass",
  "Ingredients": [
    "40 ml Blended Scotch whisky",
    "20 ml Bénédictine D.O.M. liqueur",
    "2 dash Angostura Aromatic Bitters"
  ],
  "Instructions": [
    "Select and pre-chill a Nick & Nora glass .",
    "Prepare garnish of lemon zest twist.",
    "STIR all ingredients with ice.",
    "FINE STRAIN into chilled glass.",
    "EXPRESS lemon zest twist over the cocktail and use as garnish."
  ],
  "Review": "Scotch and Bénédictine complement each other in this herbal cocktail which is balanced by the addition of bitters.",
  "History": "",
  "Nutrition": "One serving of Scottish Gypsy contains 154 calories",
  "Alcohol_Content": [
    [
      "1.4 standard drinks"
    ],
    [
      "31.53% alc./vol. (31.53° proof)"
    ],
    [
      "19.1 grams of pure alcohol"
    ]
  ],
  "Garnish": ""
}