{
  "Url": "https://www.diffordsguide.com/cocktails/recipe/2575/sentimental-melody",
  "Name": "Sentimental Melody",
  "Glass": "Martini glass",
  "Ingredients": [
    "2 barspoon Grapefruit preserve",
    "60 ml Light white rum (charcoal-filtered 1-4 years old)",
    "7.5 ml De Kuyper Triple Sec (40%)",
    "15 ml Elderflower liqueur",
    "22.5 ml Cranberry juice (sweetened)",
    "7.5 ml Pomegranate juice",
    "15 ml Lime juice (freshly squeezed)"
  ],
  "Instructions": [
    "Select and pre-chill a Martini glass .",
    "Prepare garnish of orange zest twist (flamed).",
    "STIR grapefruit preserve and rum in base of a shaker to dissolve the preserve.",
    "Add other ingredients and SHAKE with ice.",
    "FINE STRAIN into chilled glass.",
    "EXPRESS orange zest twist over the cocktail and use as garnish."
  ],
  "Review": "A twisted Daiquiri with rich berry fruit.",
  "History": "Adapted from a recipe created in 2008 by Peter Dorelli , London, England.",
  "Nutrition": "",
  "Alcohol_Content": [
    [
      "1.6 standard drinks"
    ],
    [
      "17.3% alc./vol. (17.3° proof)"
    ],
    [
      "22.1 grams of pure alcohol"
    ]
  ],
  "Garnish": ""
}