{
  "Url": "https://www.diffordsguide.com/cocktails/recipe/1764/seventh-heaven-no2",
  "Name": "Seventh Heaven No.2",
  "Glass": "",
  "Ingredients": [
    "45 ml Hayman's London Dry Gin",
    "15 ml Luxardo Maraschino liqueur",
    "10 ml Pink grapefruit juice (freshly squeezed)",
    "10 ml Chilled water omit if using wet ice"
  ],
  "Instructions": [
    "Select and pre-chill a Coupe glass .",
    "Prepare garnish of mint sprigs bouquet pegged to rim.",
    "SHAKE all ingredients with ice.",
    "FINE STRAIN into chilled glass."
  ],
  "Review": "Grapefruit citrus bitterness balances rich floral maraschino liqueur in this delicately balanced gin-based cocktail.",
  "History": "Adapted from a recipe in Harry Craddock's 1930 The Savoy Cocktail Book : \" SEVENTH HEAVEN COCKTAIL. (No.2) 1 Tablespoonful Grapefruit Juice. ¼ Maraschino ¾ Dry Gin. Stir well and place a sprig of green Mint on top. \"",
  "Nutrition": "One serving of Seventh Heaven No.2 contains 139 calories",
  "Alcohol_Content": [
    [
      "1.2 standard drinks"
    ],
    [
      "21.45% alc./vol. (21.45° proof)"
    ],
    [
      "17.2 grams of pure alcohol"
    ]
  ],
  "Garnish": ""
}