{
  "Url": "https://www.diffordsguide.com/cocktails/recipe/1827/sir-thomas",
  "Name": "Sir Thomas",
  "Glass": "",
  "Ingredients": [
    "40 ml Bourbon whiskey",
    "10 ml De Kuyper Triple Sec (40%)",
    "10 ml Heering Cherry Liqueur",
    "10 ml Strucchi Rosso Vermouth"
  ],
  "Instructions": [
    "Select and pre-chill a Nick & Nora glass .",
    "Prepare garnish of Luxardo Maraschino Cherry .",
    "STIR all ingredients with ice.",
    "FINE STRAIN into chilled glass.",
    "Garnish with maraschino cherry."
  ],
  "Review": "Akin to a fruit laced Sweet Manhattan .",
  "History": "Created in 2005 by Tom Ward, London, England.",
  "Nutrition": "One serving of Sir Thomas contains 172 calories",
  "Alcohol_Content": [
    [
      "1.5 standard drinks"
    ],
    [
      "29.25% alc./vol. (29.25° proof)"
    ],
    [
      "20.5 grams of pure alcohol"
    ]
  ],
  "Garnish": ""
}