{
  "Url": "https://www.diffordsguide.com/cocktails/recipe/2952/strawberry-on-acid",
  "Name": "Strawberry on Acid",
  "Glass": "Flute glass",
  "Ingredients": [
    "3 fresh Strawberries (hulled, small & ripe)",
    "45 ml Ketel One Vodka",
    "22.5 ml Giffard Fraise des Bois liqueur",
    "5 ml Balsamic vinegar of Modena",
    "1 grind Black pepper",
    "75 ml Brut champagne/sparkling wine"
  ],
  "Instructions": [
    "MUDDLE strawberries in base of shaker. Add next 4 ingredients, SHAKE with ice and fine strain into chilled glass. TOP with champagne."
  ],
  "Review": "Rich fruity strawberry, balanced and made interesting by vodka, balsamic vinegar and black pepper tingle.",
  "History": "Adapted from a cocktail discovered in 2010 at Bordeaux Quay in Bristol, England.",
  "Nutrition": "",
  "Alcohol_Content": [],
  "Garnish": "Balsamic covered strawberry"
}