{
  "Url": "https://www.diffordsguide.com/cocktails/recipe/3723/sunny-side-up",
  "Name": "Sunny Side Up",
  "Glass": "Highball (max 10oz/300ml)",
  "Ingredients": [
    "45 ml Cognac (brandy)",
    "15 ml Luxardo Aperitivo (Aperol-style liqueur)",
    "10 ml Americano bianco",
    "10 ml Lemon juice (freshly squeezed)",
    "20 ml Pink grapefruit juice (freshly squeezed)",
    "10 ml Sugar syrup 'rich' (2 sugar to 1 water, 65.0°Brix)",
    "2 dash Rhubarb bitters"
  ],
  "Instructions": [
    "Select and pre-chill a Highball (max 10oz/300ml) glass .",
    "Prepare garnish of dehydrated grapefruit & rhubarb slice.",
    "SHAKE all ingredients with ice.",
    "FINE STRAIN into chilled glass."
  ],
  "Review": "Bittersweet zesty citrus and cognac with aromatic wine.",
  "History": "Adapted from a drink created in 2015 by Christopher McQuillan at Am:pm, Belfast, Northern Ireland.",
  "Nutrition": "One serving of Sunny Side Up contains 200 calories",
  "Alcohol_Content": [
    [
      "1 standard drinks"
    ],
    [
      "13.08% alc./vol. (13.08° proof)"
    ],
    [
      "14.5 grams of pure alcohol"
    ]
  ],
  "Garnish": ""
}