{
  "Url": "https://www.diffordsguide.com/cocktails/recipe/3894/the-haole",
  "Name": "The Haole",
  "Glass": "Highball (max 10oz/300ml)",
  "Ingredients": [
    "45 ml Bacardi Carta Blanca Superior White Rum",
    "10 ml Strucchi Bianco Vermouth",
    "15 ml Pineapple sugar syrup",
    "20 ml Lemon juice (freshly squeezed)",
    "90 ml Thomas Henry Ginger Ale"
  ],
  "Instructions": [
    "SHAKE first 4 ingredients with ice and strain into ice-filled glass. TOP with ginger ale, stir and serve."
  ],
  "Review": "Simple but very tasty and refreshing.",
  "History": "Thai Bacardí Legacy 2016 winning cocktail winning cocktail by Mitchell Kai Lum, Vertigo & Vertigo Too, Bangkok.",
  "Nutrition": "One serving of The Haole contains 189 calories",
  "Alcohol_Content": [
    [
      "1 standard drinks"
    ],
    [
      "7.55% alc./vol. (7.55° proof)"
    ],
    [
      "13.6 grams of pure alcohol"
    ]
  ],
  "Garnish": "Pineapple wheel"
}