{
  "Url": "https://www.diffordsguide.com/cocktails/recipe/4019/the-globetrotter",
  "Name": "The Globetrotter",
  "Glass": "Coupe glass",
  "Ingredients": [
    "40 ml Bacardi Carta Blanca Superior White Rum",
    "10 ml Peachtree peach schnapps",
    "20 ml *Special ingredient #1 (see above)",
    "20 ml Earl Grey tea (cold)",
    "10 ml Lemon juice (freshly squeezed)",
    "5 ml Sugar syrup 'rich' (2 sugar to 1 water, 65.0°Brix)"
  ],
  "Instructions": [
    "SHAKE all ingredients with ice and fine strain into chilled glass. Special ingredient #1 : Quince juice"
  ],
  "Review": "",
  "History": "Polish Bacardí Legacy 2014 winning cocktail created by Rafal Nawrot at Sky Bar in Qubus Hotel-Prestige, Katowice, Poland.",
  "Nutrition": "One serving of The Globetrotter contains 129 calories",
  "Alcohol_Content": [
    [
      "0.9 standard drinks"
    ],
    [
      "11.91% alc./vol. (11.91° proof)"
    ],
    [
      "12.5 grams of pure alcohol"
    ]
  ],
  "Garnish": "Blueberry, lemon zest twist & mint sprig."
}