{
  "Url": "https://www.diffordsguide.com/cocktails/recipe/3709/winter-clove",
  "Name": "Winter Clove",
  "Glass": "Coupe glass",
  "Ingredients": [
    "3 whole Clove",
    "40 ml Cognac (brandy)",
    "20 ml Mandarine Napoleon liqueur",
    "5 ml Torabhaig Peated Single Malt Whisky",
    "3 dash Bob's Chocolate bitters"
  ],
  "Instructions": [
    "Select and pre-chill a Coupe glass .",
    "Prepare garnish of orange zest twist with a flamed clove.",
    "STIR all ingredients with ice.",
    "FINE STRAIN into chilled glass."
  ],
  "Review": "Zesty mandarin orange and cognac with a hint of smoky peat and clove spice.",
  "History": "Adapted from a recipe created in 2015 by Eric Tinca at Love die Late, Great Portland Street, London, England.",
  "Nutrition": "",
  "Alcohol_Content": [],
  "Garnish": ""
}